das/__init__.py
das/annot.py
das/augmentation.py
das/block_stratify.py
das/cli.py
das/data.py
das/data_hash.py
das/evaluate.py
das/event_utils.py
das/io.py
das/loss.py
das/make_dataset.py
das/menagerie.py
das/models.py
das/models_legacy.py
das/npy_dir.py
das/postprocessing.py
das/predict.py
das/pulse_utils.py
das/segment_utils.py
das/spec_utils.py
das/tracking.py
das/train.py
das/train_tune.py
das/utils.py
das/utils_plot.py
das/kapre/LICENSE.txt
das/kapre/README.md
das/kapre/__init__.py
das/kapre/augmentation.py
das/kapre/backend.py
das/kapre/backend_keras.py
das/kapre/filterbank.py
das/kapre/time_frequency.py
das/kapre/utils.py
das/morpholayers/LICENSE
das/morpholayers/README.md
das/morpholayers/__init__.py
das/morpholayers/constraints.py
das/morpholayers/initializers.py
das/morpholayers/layers.py
das/morpholayers/regularizers.py
das/tcn/LICENSE
das/tcn/README.md
das/tcn/__init__.py
das/tcn/tcn.py
das/tcn/tcn_new.py
das-0.32.11.dist-info/entry_points.txt
das-0.32.11.dist-info/licenses/LICENSE
das-0.32.11.dist-info/WHEEL
das-0.32.11.dist-info/METADATA
das-0.32.11.dist-info/RECORD
