Metadata-Version: 2.4
Name: das
Version: 0.32.11
Summary: DAS
Author-email: Jan Clemens <clemensjan@googlemail.com>
Requires-Python: >=3.10
Classifier: License :: OSI Approved :: Apache Software License
License-File: LICENSE
Requires-Dist: scipy
Requires-Dist: scikit-learn
Requires-Dist: matplotlib
Requires-Dist: pandas
Requires-Dist: matplotlib_scalebar
Requires-Dist: xarray-behave
Requires-Dist: tqdm
Requires-Dist: zarr<3
Requires-Dist: numpy==1.26.4 ; platform_system == "Windows"
Requires-Dist: tensorflow==2.15.1 ; platform_system == "Darwin"
Requires-Dist: tensorflow-metal==1.1.0 ; platform_system == "Darwin"
Requires-Dist: tensorflow==2.10.* ; platform_system == "Windows"
Requires-Dist: tensorflow==2.13 ; platform_system == "Linux"
Requires-Dist: pytest ; extra == "dev"
Requires-Dist: flit ; extra == "dev"
Project-URL: documentation, https://janclemenslab.org/das/
Project-URL: source, https://github.com/janclemenslab/das
Provides-Extra: dev
